twissgrid/__init__.py
twissgrid/__main__.py
TwissGrid-0.3.dist-info/LICENSE
TwissGrid-0.3.dist-info/METADATA
TwissGrid-0.3.dist-info/WHEEL
TwissGrid-0.3.dist-info/top_level.txt
TwissGrid-0.3.dist-info/RECORD
