Metadata-Version: 2.1
Name: TwissGrid
Version: 0.3
Summary: Visualize Twiss parameters for one- or two-dimensional grid scan of lattice parameters.
Home-page: https://gitlab.com/Dominik1123/twissgrid
Author: Dominik Vilsmeier
Author-email: d.vilsmeier@gsi.de
License: MIT
Keywords: MADX,lattice,Twiss,parameter scan,visualization
Platform: UNKNOWN
Classifier: Development Status :: 4 - Beta
Classifier: Intended Audience :: Science/Research
Classifier: License :: OSI Approved :: MIT License
Classifier: Programming Language :: Python :: 3.7
Classifier: Programming Language :: Python :: 3.8
Classifier: Topic :: Scientific/Engineering :: Physics
Classifier: Topic :: Scientific/Engineering :: Visualization
Requires-Python: >=3.7
Requires-Dist: cpymad
Requires-Dist: matplotlib
Requires-Dist: numpy
